mogpjax/__init__.py
MOGPJax-0.0.1.dist-info/METADATA
MOGPJax-0.0.1.dist-info/WHEEL
MOGPJax-0.0.1.dist-info/top_level.txt
MOGPJax-0.0.1.dist-info/RECORD
