Metadata-Version: 2.1
Name: MOGPJax
Version: 0.0.1
Summary: Didactic multi-output Gaussian processes in Jax.
Home-page: UNKNOWN
Author: Daniel Dodd, Thomas Pinder
Author-email: d.dodd1@lancaster.ac.uk, t.pinder2@lancaster.ac.uk
License: LICENSE
Project-URL: Documentation, https://mogpjax.readthedocs.io/en/latest/
Project-URL: Source, https://github.com/daniel-dodd/MOGPJax
Keywords: multi-output-gaussian-processes jax machine-learning bayesian
Platform: UNKNOWN
Requires-Dist: jax (==0.3.2)
Requires-Dist: jaxlib (==0.3.2)
Requires-Dist: optax (>=0.1.0)
Requires-Dist: chex (==0.1.3)
Requires-Dist: distrax (>=0.1.2)
Requires-Dist: tensorflow (==2.8.1)
Requires-Dist: tensorflow-probability (==0.16.0)
Requires-Dist: tqdm (>=4.0.0)
Requires-Dist: ml-collections (==0.1.0)
Requires-Dist: gpjax (==0.4.6)
Provides-Extra: dev
Requires-Dist: black ; extra == 'dev'
Requires-Dist: isort ; extra == 'dev'
Requires-Dist: pylint ; extra == 'dev'
Requires-Dist: flake8 ; extra == 'dev'
Provides-Extra: docs
Requires-Dist: furo ; extra == 'docs'
Provides-Extra: tests
Requires-Dist: pytest ; extra == 'tests'
